waveletvit/__init__.py
waveletvit-0.0.0.dist-info/METADATA
waveletvit-0.0.0.dist-info/WHEEL
waveletvit-0.0.0.dist-info/licenses/LICENSE
waveletvit-0.0.0.dist-info/RECORD
