Metadata-Version: 2.4
Name: WaveletViT
Version: 0.0.0
Summary: Discrete Wavelet Bank D-dimensional I/O Vision Transformer
Project-URL: Homepage, https://github.com/kkt-ee/WaveletViT
Project-URL: Issues, https://github.com/kkt-ee/WaveletViT/issues
Author-email: Kishore Kumar Tarafdar <kkt.ee.ai@gmail.com>
License-Expression: GPL-3.0-or-later
License-File: LICENSE
Classifier: Intended Audience :: Science/Research
Classifier: Operating System :: OS Independent
Classifier: Programming Language :: Python :: 3
Classifier: Topic :: Scientific/Engineering
Requires-Python: >=3.9
